setup.cfg
setup.py
CalcSquare/CalcSquare.py
CalcSquare/__init__.py
CalcSquare.egg-info/PKG-INFO
CalcSquare.egg-info/SOURCES.txt
CalcSquare.egg-info/dependency_links.txt
CalcSquare.egg-info/not-zip-safe
CalcSquare.egg-info/top_level.txt