Metadata-Version: 1.0
Name: CalcSquare
Version: 1.12
Summary: Calculate the objects square from photo
Home-page: UNKNOWN
Author: UNKNOWN
Author-email: gavrilyak.mikhail@gmail.com
License: UNKNOWN
Platform: UNKNOWN
